diffmatch.py
diffmatch-0.1.0.dist-info/licenses/LICENSE
diffmatch-0.1.0.dist-info/METADATA
diffmatch-0.1.0.dist-info/WHEEL
diffmatch-0.1.0.dist-info/entry_points.txt
diffmatch-0.1.0.dist-info/top_level.txt
diffmatch-0.1.0.dist-info/RECORD
