Metadata-Version: 2.4
Name: diffmatch
Version: 0.1.0
Summary: Commit-diff auditor. commitlint checks format. diffmatch checks truth.
Author-email: fd2 <fd2@valoryxeu.com>
License: MIT
Project-URL: Homepage, https://github.com/diffmatch-dev/diffmatch
Project-URL: Repository, https://github.com/diffmatch-dev/diffmatch
Project-URL: Issues, https://github.com/diffmatch-dev/diffmatch/issues
Keywords: git,commit,lint,diff,audit,conventional-commits
Classifier: Development Status :: 4 - Beta
Classifier: Environment :: Console
Classifier: Intended Audience :: Developers
Classifier: License :: OSI Approved :: MIT License
Classifier: Operating System :: OS Independent
Classifier: Programming Language :: Python :: 3
Classifier: Programming Language :: Python :: 3.8
Classifier: Programming Language :: Python :: 3.9
Classifier: Programming Language :: Python :: 3.10
Classifier: Programming Language :: Python :: 3.11
Classifier: Programming Language :: Python :: 3.12
Classifier: Programming Language :: Python :: 3.13
Classifier: Topic :: Software Development :: Quality Assurance
Classifier: Topic :: Software Development :: Version Control :: Git
Requires-Python: >=3.8
License-File: LICENSE
Dynamic: license-file
